informverify/__init__.py
informverify-0.1.5.dist-info/LICENSE
informverify-0.1.5.dist-info/METADATA
informverify-0.1.5.dist-info/WHEEL
informverify-0.1.5.dist-info/entry_points.txt
informverify-0.1.5.dist-info/top_level.txt
informverify-0.1.5.dist-info/RECORD
